{
    "hits":[
        {
            "name":"The Leela Palace New Delhi",
            "location": "New Delhi"
        },
        {
            "name":"Taj Lake Palace, Udaipur",
            "location":"Rajasthan,Udaipur"
            
        },
        { 
            "name":"The Oberoi, New Delhi",
            " location ":"New Delhi"
          
        },
        {
            
            "name":"The Lodhi",

            " location": "New Delhi"
       
        },
        { 
            "name":"Rajmahal Palace Raas Jaipur",
            "location":"Rajasthan, Jaipur"
            
        },
        {
            

            "name":"Suryagarh",
            "location":"Jaisalmer, Rajasthan"
        },
        {
            
            "name":"Taj Palace, New Delhi",
            "location":"New Delhi"
        }
    ]
}
